dt_cyclonedx_conan/__init__.py
dt_cyclonedx_conan/cdx.py
dt_cyclonedx_conan/cli.py
dt_cyclonedx_conan/generate.py
dt_cyclonedx_conan/utils.py
dt_cyclonedx_conan-0.1.1.dist-info/METADATA
dt_cyclonedx_conan-0.1.1.dist-info/WHEEL
dt_cyclonedx_conan-0.1.1.dist-info/entry_points.txt
dt_cyclonedx_conan-0.1.1.dist-info/RECORD
